sequential_circuits/Universal_Binary_Counter/univ_bin_couter.v
module univ_vin_counter #(parameter N=8) (clk, reset, 
			syn_clr, load, en , up, d, max_tick, min_tick, q);
// init port
input wire clk, reset, syn_clr, load, en, up;
input wire[N-1:0] d;
output wire max_tick, min_tick;
output wire [N-1:0] q;

// Signal declaration
reg [N-1:0] r_reg, r_next;

always @(posedge clk, posedge reset)
	if (reset)
		r_reg <= 0;
	else
		r_reg <= r_next;
// next state logic
always @*
	if(syn_clr)
		r_next = 0;
	else if (load)
		r_next = d;
	else if (en & up)
		r_next = r_reg + 1;
	else if (en & ~up)
		r_next = r_reg - 1;
	else
		r_next = r_reg;
//output
assign q = r_reg;
assign max_tick = (r_reg == 2**N-1) ? 1'b1: 1'b0;
assign min_tick = (r_reg == 0) ? 1'b1: 1'b0;
endmodule

sequential_circuits/Universal_Binary_Counter/univ_bin_couter_tb.v
//`timescale 1ns /1ns
`include "univ_bin_couter.v"

module univ_bin_counter_tb;
	localparam T = 20;
	reg clk, reset;
	reg syn_clr, load, en, up;
	reg[2:0] d;
	wire max_tick, min_tick;
	wire [2:0] q;
	// unit
	univ_vin_counter #(.N(3)) uut (.clk(clk), .reset(reset),
		.syn_clr(syn_clr), .load(load), .en(en), .up(up), 
		.d(d), .max_tick(max_tick), .min_tick(min_tick),
		.q(q));

	// clock 20ns clock running forever
	always 
	begin
		clk = 1'b1;
		#(T/2);
		clk = 1'b0;
		#(T/2);
	end

	// reset for the first half cycle
	initial
	begin 
		reset = 1'b1;
		#(T/2);
		reset = 1'b0;
	end

	initial begin 
        $dumpfile("univ_bin_counter_tb.vcd");
        $dumpvars(0,univ_bin_counter_tb);
	end
    
	initial 
	begin
       // $dumpfile("univ_bin_counter_tb.vcd");
       // $dumpvars(0,univ_bin_counter_tb);
		// initial input
		syn_clr = 1'b0;
		load = 1'b0;
		en = 1'b0;
		up = 1'b1;
		d = 3'b000;
		@(negedge reset);
		@(negedge clk);
		// test load
		load = 1'b1;
		d = 3'b011;
		@(negedge clk);
		load = 1'b0;
		repeat(2); @(negedge clk);
		// test syn_clear
		syn_clr = 1'b1;
		@(negedge clk);
		syn_clr = 1'b0;
		// test up counter and pause
		en = 1'b1;
		up = 1'b1;
		repeat(10) @(negedge clk);
		en = 1'b0;
		repeat(2); @(negedge clk);
		en = 1'b1;
		repeat(2); @(negedge clk);
		// test down counter
		up = 1'b0;
		repeat(10) @(negedge clk);
		// continue until q = 2
		wait(q==2);
		@(negedge clk);
		up = 1'b1;
		// continue until min_tick becomes 1
		@(negedge clk);
		wait(min_tick);
		@(negedge clk);
		up = 1'b0;
		// absolute delay
		#(4*T);
		en = 1'b0;
		#(4*T);
        $display("Finish Test");
        $finish;
    end
endmodule

sequential_circuits/Universal_Binary_Counter/univ_bin_counter_tb.vcd
$date
	Wed Apr 10 20:46:58 2024
$end
$version
	Icarus Verilog
$end
$timescale
	1s
$end
$scope module univ_bin_counter_tb $end
$var wire 3 ! q [2:0] $end
$var wire 1 " min_tick $end
$var wire 1 # max_tick $end
$var parameter 32 $ T $end
$var reg 1 % clk $end
$var reg 3 & d [2:0] $end
$var reg 1 ' en $end
$var reg 1 ( load $end
$var reg 1 ) reset $end
$var reg 1 * syn_clr $end
$var reg 1 + up $end
$scope module uut $end
$var wire 1 % clk $end
$var wire 3 , d [2:0] $end
$var wire 1 ' en $end
$var wire 1 ( load $end
$var wire 3 - q [2:0] $end
$var wire 1 ) reset $end
$var wire 1 * syn_clr $end
$var wire 1 + up $end
$var wire 1 " min_tick $end
$var wire 1 # max_tick $end
$var parameter 32 . N $end
$var reg 3 / r_next [2:0] $end
$var reg 3 0 r_reg [2:0] $end
$upscope $end
$upscope $end
$enddefinitions $end
$comment Show the parameter values. $end
$dumpall
b11 .
b10100 $
$end
#0
$dumpvars
b0 0
b0 /
b0 -
b0 ,
1+
0*
1)
0(
0'
b0 &
1%
0#
1"
b0 !
$end
#10
0)
0%
#20
1%
#30
b11 /
b11 &
b11 ,
1(
0%
#40
0"
b11 !
b11 -
b11 0
1%
#50
0(
0%
#60
1%
#70
b0 /
1*
0%
#80
1"
b0 !
b0 -
b0 0
1%
#90
b1 /
1'
0*
0%
#100
b10 /
0"
b1 !
b1 -
b1 0
1%
#110
0%
#120
b11 /
b10 !
b10 -
b10 0
1%
#130
0%
#140
b100 /
b11 !
b11 -
b11 0
1%
#150
0%
#160
b101 /
b100 !
b100 -
b100 0
1%
#170
0%
#180
b110 /
b101 !
b101 -
b101 0
1%
#190
0%
#200
b111 /
b110 !
b110 -
b110 0
1%
#210
0%
#220
b0 /
1#
b111 !
b111 -
b111 0
1%
#230
0%
#240
b1 /
0#
1"
b0 !
b0 -
b0 0
1%
#250
0%
#260
b10 /
0"
b1 !
b1 -
b1 0
1%
#270
0%
#280
b11 /
b10 !
b10 -
b10 0
1%
#290
b10 /
0'
0%
#300
1%
#310
b11 /
1'
0%
#320
b100 /
b11 !
b11 -
b11 0
1%
#330
b10 /
0+
0%
#340
b1 /
b10 !
b10 -
b10 0
1%
#350
0%
#360
b0 /
b1 !
b1 -
b1 0
1%
#370
0%
#380
b111 /
1"
b0 !
b0 -
b0 0
1%
#390
0%
#400
b110 /
1#
0"
b111 !
b111 -
b111 0
1%
#410
0%
#420
b101 /
0#
b110 !
b110 -
b110 0
1%
#430
0%
#440
b100 /
b101 !
b101 -
b101 0
1%
#450
0%
#460
b11 /
b100 !
b100 -
b100 0
1%
#470
0%
#480
b10 /
b11 !
b11 -
b11 0
1%
#490
0%
#500
b1 /
b10 !
b10 -
b10 0
1%
#510
0%
#520
b0 /
b1 !
b1 -
b1 0
1%
#530
0%
#540
b111 /
1"
b0 !
b0 -
b0 0
1%
#550
0%
#560
b110 /
1#
0"
b111 !
b111 -
b111 0
1%
#570
0%
#580
b101 /
0#
b110 !
b110 -
b110 0
1%
#590
0%
#600
b100 /
b101 !
b101 -
b101 0
1%
#610
0%
#620
b11 /
b100 !
b100 -
b100 0
1%
#630
0%
#640
b10 /
b11 !
b11 -
b11 0
1%
#650
0%
#660
b1 /
b10 !
b10 -
b10 0
1%
#670
b11 /
1+
0%
#680
b100 /
b11 !
b11 -
b11 0
1%
#690
0%
#700
b101 /
b100 !
b100 -
b100 0
1%
#710
0%
#720
b110 /
b101 !
b101 -
b101 0
1%
#730
0%
#740
b111 /
b110 !
b110 -
b110 0
1%
#750
0%
#760
b0 /
1#
b111 !
b111 -
b111 0
1%
#770
0%
#780
b1 /
0#
1"
b0 !
b0 -
b0 0
1%
#790
b111 /
0+
0%
#800
b110 /
1#
0"
b111 !
b111 -
b111 0
1%
#810
0%
#820
b101 /
0#
b110 !
b110 -
b110 0
1%
#830
0%
#840
b100 /
b101 !
b101 -
b101 0
1%
#850
0%
#860
b11 /
b100 !
b100 -
b100 0
1%
#870
b100 /
0%
0'
