sequential_circuits/fsm/fsm_eg_mult_seg.v
module fsm_eg_mult_seg
(
	input wire clk, reset,
	input wire a, b, 
	output wire y0, y1
);

	// symbolic state declaration
	localparam [1:0]	s0 = 2'b00,
										s1 = 2'b01,
										s2 = 2'b10;

	// signal declaration
	reg [1:0] state_reg, state_next;

	// state register
	always @(posedge clk, posedge reset)	
		if (reset)
			state_reg <= s0;
		else
			state_reg <= state_next;

	// next state logic
	always @*
		case (state_reg)
			s0: if (a)
						if (b)
							state_next = s2;
						else 
							state_next = s1;
					else
						state_next = s0;
			
			//-- 
			s1: if (a)
						state_next = s0;
					else
						state_next = s1;

			//--
			s2: state_next = s0;
			
			default: state_next = s0;
		endcase

	// Moore output logic
	assign y1 = (state_reg==s0) || (state_reg==s1);

	// Mealy output logic
	assign y0 = (state_reg==s0) & a & b;

endmodule

FSM/simpleFSM/fsm_eg_mult_seg_tb.v
`timescale 1 ns/10 ps
`include "fsm_eg_mult_seg.v"
module fsm_eg_mult_seg_tb ();
	// declaration
	localparam T=20; //clock period
	reg clk, reset;
	reg a, b;
	wire y0, y1;
	// design under test
	fsm_eg_mult_seg dut (.clk(clk), 
	.reset(reset), .a(a), .b(b), 
	.y0(y0), .y1(y1));
	// clock
	always
	begin
		clk = 1'b1;
		#(T/2);
		clk = 1'b0;
		#(T/2);
	end
	//reset 
	initial 
	begin
		reset = 1'b1;
		#(T); #(T/2);
		reset = 1'b0;
	end

  initial begin 
    $dumpfile("fsm_eg_mult_seg_tb.vcd");
    $dumpvars(0, fsm_eg_mult_seg_tb);
  end
	// stimulus
	initial
	begin
		// wait for half cycle
		#(T/2);
		a = 1'b0;
		b = 1'b1;
		
		#(4*T);
		a = 1'b1;
		
		#(2*T);
		a = 1'b1;
		b = 1'b0;
		
		#(1*T);
		a = 1'b0;

		#(3*T);
		a = 1'b1;
		
		#(2*T);
    $finish;
	end

endmodule

FSM/simpleFSM/fsm_eg_mult_seg_tb.vcd
$date
	Wed Apr 17 13:11:28 2024
$end
$version
	Icarus Verilog
$end
$timescale
	10ps
$end
$scope module fsm_eg_mult_seg_tb $end
$var wire 1 ! y1 $end
$var wire 1 " y0 $end
$var parameter 32 # T $end
$var reg 1 $ a $end
$var reg 1 % b $end
$var reg 1 & clk $end
$var reg 1 ' reset $end
$scope module dut $end
$var wire 1 $ a $end
$var wire 1 % b $end
$var wire 1 & clk $end
$var wire 1 ' reset $end
$var wire 1 " y0 $end
$var wire 1 ! y1 $end
$var parameter 2 ( s0 $end
$var parameter 2 ) s1 $end
$var parameter 2 * s2 $end
$var reg 2 + state_next [1:0] $end
$var reg 2 , state_reg [1:0] $end
$upscope $end
$upscope $end
$enddefinitions $end
$comment Show the parameter values. $end
$dumpall
b10 *
b1 )
b0 (
b10100 #
$end
#0
$dumpvars
b0 ,
b0 +
1'
1&
x%
x$
x"
1!
$end
#1000
0"
1%
0$
0&
#2000
1&
#3000
0&
0'
#4000
1&
#5000
0&
#6000
1&
#7000
0&
#8000
1&
#9000
1"
b10 +
0&
1$
#10000
0"
b0 +
0!
b10 ,
1&
#11000
0&
#12000
1"
b10 +
1!
b0 ,
1&
#13000
0"
b1 +
0&
0%
#14000
b0 +
b1 ,
1&
#15000
b1 +
0&
0$
#16000
1&
#17000
0&
#18000
1&
#19000
0&
#20000
1&
#21000
b0 +
0&
1$
#22000
b1 +
b0 ,
1&
#23000
0&
#24000
b0 +
b1 ,
1&
