Combinational_circuits/FullAdder1bit/FullAdder1bit.v
module FullAdder1bit( w0, w1, cin, y, cout);
    // w0, w1, cin, y, cout
    input wire w0, w1, cin;
    output reg y, cout;

    reg line1, line2, line3;

    always @(w0 or w1 or cin) begin
        line1 = w0^w1;
        y = cin^line1;

        line2 = w0&w1;
        line3 = line1&cin;
        cout = line2|line3;
    end
endmodule

Combinational_circuits/FullAdder1bit/FullAdder1bit_tb.v
`timescale 1ns / 1ns
`include "FullAdder1bit.v"

module FullAdder1bit_tb;
    reg w0, w1, cin;
    wire y, cout;

    //FullAdder1bit(w0, w1, cin, y, cout);
    FullAdder1bit fulladder(w0, w1, cin, y, cout);
    
    initial begin
        $dumpfile("FullAdder1bit_tb.vcd");
        $dumpvars(0, FullAdder1bit_tb);

        w0 = 1'b0; w1 = 1'b0; cin = 1'b0;
        #20
        w0 = 1'b0; w1 = 1'b0; cin = 1'b1;
        #20
        w0 = 1'b0; w1 = 1'b1; cin = 1'b0;
        #20
        w0 = 1'b0; w1 = 1'b1; cin = 1'b1;
        #20
        w0 = 1'b1; w1 = 1'b0; cin = 1'b0;
        #20
        w0 = 1'b1; w1 = 1'b0; cin = 1'b1;
        #20
        w0 = 1'b1; w1 = 1'b1; cin = 1'b0;
        #20
        w0 = 1'b1; w1 = 1'b1; cin = 1'b1;
        #20
        
        $finish;
    end
endmodule

FullAdder1bit/FullAdder1bit_tb.vcd
$date
	Sat Mar 23 14:05:43 2024
$end
$version
	Icarus Verilog
$end
$timescale
	1ns
$end
$scope module FullAdder1bit_tb $end
$var wire 1 ! y $end
$var wire 1 " cout $end
$var reg 1 # cin $end
$var reg 1 $ w0 $end
$var reg 1 % w1 $end
$scope module fulladder $end
$var wire 1 # cin $end
$var wire 1 $ w0 $end
$var wire 1 % w1 $end
$var reg 1 " cout $end
$var reg 1 & line1 $end
$var reg 1 ' line2 $end
$var reg 1 ( line3 $end
$var reg 1 ! y $end
$upscope $end
$upscope $end
$enddefinitions $end
$comment Show the parameter values. $end
$dumpall
$end
#0
$dumpvars
0(
0'
0&
0%
0$
0#
0"
0!
$end
#20
1!
1#
#40
1&
0#
1%
#60
1"
1(
0!
1#
#80
0"
0(
1!
0#
0%
1$
#100
1"
1(
0!
1#
#120
0(
1'
0&
0#
1%
#140
1!
1#
