Combinational_circuits/FMUX2_1/MUX2_1.v
module MUX2_1(w0, w1, s, y);

    input wire w0, w1, s;
    output wire y;

    assign y = s? w1:w0;
endmodule

FMUX2_1/MUX2_1_testbend.v
`timescale 1ns / 1ns
`include "MUX2_1.v"

module MUX2_1_testbend;
    wire Y;
    reg a,b,s;

MUX2_1 mux(.w0(a),.w1(b), .s(s), .y(Y));

initial begin
    $dumpfile("MUX2_1_testbend.vcd");
    $dumpvars(0, MUX2_1_testbend);

    a = 0;
    b = 0;
    s = 0;
    #20;
    a = 0;
    b = 1;
    s = 0;
    #20;
    a = 1;
    b = 0;
    s = 0;
    #20;
    a = 1;
    b = 1;
    s = 0;
    #20;

    a = 0;
    b = 0;
    s = 1;
    #20;
    a = 0;
    b = 1;
    s = 1;
    #20;
    a = 1;
    b = 0;
    s = 1;
    #20;
    a = 1;
    b = 1;
    s = 1;
    #20;

    $display("Test Completed");
    $finish;
end
endmodule

FMUX2_1/MUX2_1_testbend.vcd
$date
	Tue Mar 19 12:13:36 2024
$end
$version
	Icarus Verilog
$end
$timescale
	1ns
$end
$scope module MUX2_1_testbend $end
$var wire 1 ! Y $end
$var reg 1 " a $end
$var reg 1 # b $end
$var reg 1 $ s $end
$scope module mux $end
$var wire 1 $ s $end
$var wire 1 " w0 $end
$var wire 1 # w1 $end
$var wire 1 ! y $end
$upscope $end
$upscope $end
$enddefinitions $end
$comment Show the parameter values. $end
$dumpall
$end
#0
$dumpvars
0$
0#
0"
0!
$end
#20
1#
#40
1!
0#
1"
#60
1#
#80
0!
1$
0#
0"
#100
1!
1#
#120
0!
0#
1"
#140
1!
1#
