sequential_circuits/DFF_with_Synchronous_enable/dff_en_2seg.v
module dff_en_2seg(clk, reset, en, d, q);
	input wire clk, reset, en, d;
	output reg q;

	// signal
	reg r_reg, r_next;
	
	// DFF
	always @(posedge clk, posedge reset)
		if (reset)
			r_reg <= 1'b0;
		else
			r_reg <= r_next;
	always @*
		if (en)
			r_next = d;
		else 
			r_next = r_reg;

	// output
	always @*
		q = r_reg;

endmodule

sequential_circuits/DFF_with_Synchronous_enable/dff_en_2seg_tb.v
`include "dff_en_2seg.v"

module dff_en_2seg_tb;
  reg clk, reset, en, d;
  wire q;

  dff_en_2seg dff (.clk(clk), .reset(reset), .en(en), .d(d), .q(q));

  initial  begin
   $dumpfile("dff_en_2seg_tb");
   $dumpvars(0, dff_en_2seg_tb);
  end

  always #2 clk = ~clk;

  initial begin
    en = 0; reset = 0; d = 0; clk = 0;
    #3; 
    repeat (6) begin
      d = $urandom_range(0, 1);
      #3;
    end
    reset = 1; #3;
    reset = 0; #3;
    en = 1; #3;
    repeat (6) begin
      d = $urandom_range(0, 1);
      #3;
    end
    en = 0; #3;
    repeat (6) begin
      d = $urandom_range(0, 1);
      #3;
    end
    $display("Complete testbench");
    $finish;
  end
endmodule

sequential_circuits/DFF_with_Synchronous_enable/dff_en_2seg_tb.vcd
$date
	Sat Apr 13 13:24:23 2024
$end
$version
	Icarus Verilog
$end
$timescale
	1s
$end
$scope module dff_en_2seg_tb $end
$var wire 1 ! q $end
$var reg 1 " clk $end
$var reg 1 # d $end
$var reg 1 $ en $end
$var reg 1 % reset $end
$scope module dff $end
$var wire 1 " clk $end
$var wire 1 # d $end
$var wire 1 $ en $end
$var wire 1 % reset $end
$var reg 1 ! q $end
$var reg 1 & r_next $end
$var reg 1 ' r_reg $end
$upscope $end
$upscope $end
$enddefinitions $end
$comment Show the parameter values. $end
$dumpall
$end
#0
$dumpvars
x'
x&
0%
0$
0#
0"
x!
$end
#2
1"
#3
1#
#4
0"
#6
1"
0#
#8
0"
#10
1"
#12
0"
#14
1"
#15
1#
#16
0"
#18
1"
#20
0"
#21
0!
0&
0'
1%
#22
1"
#24
0"
0%
#26
1"
#27
1&
1$
#28
0"
#30
0&
1"
0#
#32
0"
#34
1"
#36
1&
0"
1#
#38
1!
1'
1"
#40
0"
#42
1"
#44
0"
#46
1"
#48
0"
0$
#50
1"
#52
0"
#54
1"
#56
0"
#58
1"
#60
0"
0#
