Combinational_circuits/LogicUnits/units.v
module units(i, y);
    input wire[3:0] i;
    output reg y;

    reg w1, w2;

    always @* begin
        w1 = ~(i[0] & i[1]);
        w2 = i[2] | w1;
        y = (~i[3]) & w2;
    end
endmodule

Combinational_circuits/LogicUnits/units_tb.v
`timescale 1ns / 1ns
`include "units.v"

module units_tb;
    reg[3:0] itb;
    wire ytb;

    units u(.i(itb), .y(ytb));

    initial begin
        $dumpfile("units_tb.vcd");
        $dumpvars(0, units_tb);

        itb = 4'b0000; #20
        itb = 4'b0001; #20
        itb = 4'b0010; #20
        itb = 4'b0011; #20
        itb = 4'b0100; #20
        itb = 4'b0101; #20
        itb = 4'b0110; #20
        itb = 4'b0111; #20

        itb = 4'b1000; #20
        itb = 4'b1001; #20
        itb = 4'b1010; #20
        itb = 4'b1011; #20
        itb = 4'b1100; #20
        itb = 4'b1101; #20
        itb = 4'b1110; #20
        itb = 4'b1111; #20
        
        $finish;
    end
endmodule

Combinational_circuits/LogicUnits/units_tb.vcd
$date
	Mon Mar 25 14:19:53 2024
$end
$version
	Icarus Verilog
$end
$timescale
	1ns
$end
$scope module units_tb $end
$var wire 1 ! ytb $end
$var reg 4 " itb [3:0] $end
$scope module u $end
$var wire 4 # i [3:0] $end
$var reg 1 $ w1 $end
$var reg 1 % w2 $end
$var reg 1 ! y $end
$upscope $end
$upscope $end
$enddefinitions $end
$comment Show the parameter values. $end
$dumpall
$end
#0
$dumpvars
1%
1$
b0 #
b0 "
1!
$end
#20
b1 "
b1 #
#40
b10 "
b10 #
#60
0!
0%
0$
b11 "
b11 #
#80
1!
1%
1$
b100 "
b100 #
#100
b101 "
b101 #
#120
b110 "
b110 #
#140
0$
b111 "
b111 #
#160
0!
1$
b1000 "
b1000 #
#180
b1001 "
b1001 #
#200
b1010 "
b1010 #
#220
0%
0$
b1011 "
b1011 #
#240
1%
1$
b1100 "
b1100 #
#260
b1101 "
b1101 #
#280
b1110 "
b1110 #
#300
0$
b1111 "
b1111 #
