encoder8to3/encoder8to3.v
module encoder8to3(r, Y);
    input wire[7:0] r;
    output reg[3:0] Y;

    always @* begin
        casez(r)
            8'b0???????: Y = 4'b1000;
            8'b10??????: Y = 4'b0111;
            8'b110?????: Y = 4'b0110;
            8'b1110????: Y = 4'b0101;
            8'b11110???: Y = 4'b0100;
            8'b111110??: Y = 4'b0011;
            8'b1111110?: Y = 4'b0010;
            8'b11111110: Y = 4'b0001;
            8'b11111111: Y = 4'b0000;
        endcase
    end
endmodule

Combinational_circuits/encoder8to3/encoder8to3_tb.v
`timescale 1ns / 1ns
`include "encoder8to3.v"

module encoder8to3_tb;
    wire [3:0] tb_Y;
    reg [7:0] tb_r;
    
    encoder8to3 encoder(.r(tb_r), .Y(tb_Y));

    initial begin
        $dumpfile("encoder8to3_tb.vcd");
        $dumpvars(0, encoder8to3_tb);

        tb_r= 8'b01010110;
        #20
        tb_r= 8'b10010110;
        #20
        tb_r= 8'b11010110;
        #20
        tb_r= 8'b11100110;
        #20
        tb_r= 8'b11110110;
        #20
        tb_r= 8'b11111010;
        #20
        tb_r= 8'b11111100;
        #20
        tb_r= 8'b11111110;
        #20
        tb_r= 8'b11111111;
        #20
        $display("Test completed");  // Display a message indicating test completion
        $finish;  // End simulation
    end
endmodule

encoder8to3/encoder8to3_tb.vcd
$date
	Wed Mar 20 11:18:09 2024
$end
$version
	Icarus Verilog
$end
$timescale
	1ns
$end
$scope module encoder8to3_tb $end
$var wire 4 ! tb_Y [3:0] $end
$var reg 8 " tb_r [7:0] $end
$scope module encoder $end
$var wire 8 # r [7:0] $end
$var reg 4 $ Y [3:0] $end
$upscope $end
$upscope $end
$enddefinitions $end
$comment Show the parameter values. $end
$dumpall
$end
#0
$dumpvars
b1000 $
b1010110 #
b1010110 "
b1000 !
$end
#20
b111 !
b111 $
b10010110 "
b10010110 #
#40
b110 !
b110 $
b11010110 "
b11010110 #
#60
b101 !
b101 $
b11100110 "
b11100110 #
#80
b100 !
b100 $
b11110110 "
b11110110 #
#100
b11 !
b11 $
b11111010 "
b11111010 #
#120
b10 !
b10 $
b11111100 "
b11111100 #
#140
b1 !
b1 $
b11111110 "
b11111110 #
#160
b0 !
b0 $
b11111111 "
b11111111 #
