Homework/Counter_to_100/counter_to_100.v
module counter_to_100(clk, reset, up_down, count10, count100, carry10, carry100);

  input wire clk, reset, up_down;
  output reg carry10, carry100;
  output reg[3:0] count10, count100;

  always @(posedge clk or posedge reset)
  begin 
    if(reset) begin 
      count10 = 4'b0; count100 = 4'b0;
      carry10 = 1'b0; carry100 = 1'b0;
    end 
    if(up_down) begin 
      if(count10 == 4'b1001) begin 
        carry10 = 1'b1;
        count10 <= 4'b0;
      end 
      else begin 
        carry10 = 1'b0;
        count10 <= count10 + 4'b1;
      end 
      if(carry10 == 1'b1) begin
        if (count100 == 4'b1001) begin 
        count100 <= 4'b0;
        carry100 = 1'b1;
        end
        else begin 
          count100 <= count100 + 4'b1;
          carry100 = 1'b0;
        end
      end 
    end 
    else begin 
      if(count10 == 4'b0) begin 
        carry10 = 1'b1;
        count10 <= 4'b1001;
      end 
      else begin 
        count10 <= count10 - 4'b1;
        carry10 = 0;
      end 
      if(carry10 == 1) begin 
        if (count100 == 4'b0) begin
          count100 <= 4'b1001;
          carry100 = 1;
        end
        else begin 
          count100 <= count100 - 4'b1;
          carry100 = 0;
        end
      end 
    end 
  end 
endmodule

Homework/Counter_to_100/counter_to_100_tb.v
`timescale 1ns/1ns 
`include "counter_to_100.v"

module counter_to_100_tb();
  reg clk, reset, up_down;
  wire carry10, carry100;
  wire[3:0] count10, count100;

  localparam T = 20;
  //module counter_to_100(clk, reset, up_down, count10, count100, carry10, carry100);
  counter_to_100 countBlock (clk, reset, up_down, count10, count100, carry10, carry100);

  always 
  begin 
    clk = 1'b1;
    #(T/4);
    clk = 1'b0;
    #(T/4);
  end

  initial
  begin 
  $dumpfile("counter_to_100_tb.vcd");
  $dumpvars(0, counter_to_100_tb);
  end

  initial 
  begin 
    reset <= 1; up_down <= 0; 
    #(T); reset <= 0; up_down <=1;
    #(T*10);
    //reset <= 1;
    #(T); up_down <=0;
    #(T*10);
    up_down <= 1;
    #(T*2); up_down <= 0;
    #(T*4);$finish;
  end
endmodule

Homework/Counter_to_100/counter_to_100_tb.vcd
$date
	Wed May 15 00:40:11 2024
$end
$version
	Icarus Verilog
$end
$timescale
	1ns
$end
$scope module counter_to_100_tb $end
$var wire 4 ! count100 [3:0] $end
$var wire 4 " count10 [3:0] $end
$var wire 1 # carry100 $end
$var wire 1 $ carry10 $end
$var parameter 32 % T $end
$var reg 1 & clk $end
$var reg 1 ' reset $end
$var reg 1 ( up_down $end
$scope module countBlock $end
$var wire 1 & clk $end
$var wire 1 ' reset $end
$var wire 1 ( up_down $end
$var reg 1 $ carry10 $end
$var reg 1 # carry100 $end
$var reg 4 ) count10 [3:0] $end
$var reg 4 * count100 [3:0] $end
$upscope $end
$upscope $end
$enddefinitions $end
$comment Show the parameter values. $end
$dumpall
b10100 %
$end
#0
$dumpvars
b1001 *
b1001 )
0(
1'
1&
1$
1#
b1001 "
b1001 !
$end
#5
0&
#10
1#
1$
b1001 !
b1001 *
b1001 "
b1001 )
1&
#15
0&
#20
1(
0'
1#
1$
b1001 !
b1001 *
b1001 "
b1001 )
1&
#25
0&
#30
b0 !
b0 *
b0 "
b0 )
1&
#35
0&
#40
b1 "
b1 )
0$
1&
#45
0&
#50
b10 "
b10 )
1&
#55
0&
#60
b11 "
b11 )
1&
#65
0&
#70
b100 "
b100 )
1&
#75
0&
#80
b101 "
b101 )
1&
#85
0&
#90
b110 "
b110 )
1&
#95
0&
#100
b111 "
b111 )
1&
#105
0&
#110
b1000 "
b1000 )
1&
#115
0&
#120
b1001 "
b1001 )
1&
#125
0&
#130
b1 !
b1 *
b0 "
b0 )
0#
1$
1&
#135
0&
#140
b1 "
b1 )
0$
1&
#145
0&
#150
b10 "
b10 )
1&
#155
0&
#160
b11 "
b11 )
1&
#165
0&
#170
b100 "
b100 )
1&
#175
0&
#180
b101 "
b101 )
1&
#185
0&
#190
b110 "
b110 )
1&
#195
0&
#200
b111 "
b111 )
1&
#205
0&
#210
b1000 "
b1000 )
1&
#215
0&
#220
b1001 "
b1001 )
1&
#225
0&
#230
b10 !
b10 *
b0 "
b0 )
1$
1&
#235
0&
#240
b1 "
b1 )
0(
0$
1&
#245
0&
#250
b0 "
b0 )
1&
#255
0&
#260
b1 !
b1 *
b1001 "
b1001 )
1$
1&
#265
0&
#270
b1000 "
b1000 )
0$
1&
#275
0&
#280
b111 "
b111 )
1&
#285
0&
#290
b110 "
b110 )
1&
#295
0&
#300
b101 "
b101 )
1&
#305
0&
#310
b100 "
b100 )
1&
#315
0&
#320
b11 "
b11 )
1&
#325
0&
#330
b10 "
b10 )
1&
#335
0&
#340
b1 "
b1 )
1&
#345
0&
#350
b0 "
b0 )
1&
#355
0&
#360
b0 !
b0 *
b1001 "
b1001 )
1$
1&
#365
0&
#370
b1000 "
b1000 )
0$
1&
#375
0&
#380
b111 "
b111 )
1&
#385
0&
#390
b110 "
b110 )
1&
#395
0&
#400
b101 "
b101 )
1&
#405
0&
#410
b100 "
b100 )
1&
#415
0&
#420
b11 "
b11 )
1&
#425
0&
#430
b10 "
b10 )
1&
#435
0&
#440
b1 "
b1 )
1(
1&
#445
0&
#450
b10 "
b10 )
1&
#455
0&
#460
b11 "
b11 )
1&
#465
0&
#470
b100 "
b100 )
1&
#475
0&
#480
b101 "
b101 )
0(
1&
#485
0&
#490
b100 "
b100 )
1&
#495
0&
#500
b11 "
b11 )
1&
#505
0&
#510
b10 "
b10 )
1&
#515
0&
#520
b1 "
b1 )
1&
#525
0&
#530
b0 "
b0 )
1&
#535
0&
#540
b1001 !
b1001 *
b1001 "
b1001 )
1#
1$
1&
#545
0&
#550
b1000 "
b1000 )
0$
1&
#555
0&
#560
b111 "
b111 )
1&
